{
"aliases": {
"china_customs": {
"america": "502",
"argentina": "402",
"australia": "601",
"austria": "315",
"bangladesh": "103",
"belgium": "301",
"brazil": "410",
"burma": "106",
"canada": "501",
"chile": "412",
"china": "142",
"colombia": "413",
"czechia": "352",
"denmark": "302",
"egypt": "215",
"finland": "318",
"france": "305",
"germany": "304",
"greece": "310",
"holland": "309",
"hong kong": "110",
"hungary": "321",
"india": "111",
"indonesia": "112",
"ireland": "306",
"israel": "115",
"italy": "307",
"japan": "116",
"kazakhstan": "145",
"korea": "133",
"kuwait": "118",
"malaysia": "122",
"mexico": "429",
"myanmar": "106",
"netherlands": "309",
"new zealand": "609",
"nigeria": "236",
"north korea": "109",
"norway": "326",
"oman": "126",
"pakistan": "127",
"peru": "434",
"philippines": "129",
"poland": "327",
"portugal": "311",
"prc": "142",
"qatar": "130",
"romania": "328",
"russia": "344",
"saudi arabia": "131",
"singapore": "132",
"south africa": "244",
"south korea": "133",
"spain": "312",
"sri lanka": "134",
"sweden": "330",
"switzerland": "331",
"taiwan": "143",
"thailand": "136",
"turkey": "137",
"uae": "138",
"uk": "303",
"ukraine": "347",
"united arab emirates": "138",
"united kingdom": "303",
"united states": "502",
"us": "502",
"usa": "502",
"vietnam": "141"
},
"india_trade": {
"america": "423",
"argentina": "15",
"australia": "17",
"austria": "19",
"bangladesh": "27",
"belgium": "33",
"brazil": "43",
"burma": "258",
"canada": "59",
"chile": "73",
"china": "77",
"colombia": "83",
"czechia": "98",
"denmark": "101",
"egypt": "111",
"finland": "125",
"france": "129",
"germany": "147",
"greece": "155",
"holland": "275",
"hong kong": "179",
"hungary": "181",
"indonesia": "187",
"ireland": "193",
"israel": "195",
"italy": "197",
"japan": "205",
"kazakhstan": "212",
"korea": "217",
"kuwait": "219",
"malaysia": "245",
"mexico": "259",
"myanmar": "258",
"netherlands": "275",
"new zealand": "285",
"nigeria": "291",
"north korea": "215",
"norway": "297",
"oman": "301",
"pakistan": "309",
"peru": "319",
"philippines": "323",
"poland": "325",
"portugal": "327",
"prc": "77",
"qatar": "335",
"romania": "343",
"russia": "344",
"saudi arabia": "351",
"singapore": "359",
"south africa": "365",
"south korea": "217",
"spain": "367",
"sri lanka": "369",
"sweden": "387",
"switzerland": "389",
"taiwan": "75",
"thailand": "397",
"turkey": "409",
"uae": "419",
"uk": "421",
"ukraine": "422",
"united arab emirates": "419",
"united kingdom": "421",
"united states": "423",
"us": "423",
"usa": "423",
"vietnam": "437"
},
"japan_trade": {
"america": "304",
"argentina": "413",
"australia": "601",
"austria": "225",
"bangladesh": "127",
"belgium": "208",
"brazil": "410",
"burma": "122",
"canada": "302",
"chile": "409",
"china": "105",
"colombia": "401",
"czechia": "245",
"denmark": "204",
"egypt": "506",
"finland": "222",
"france": "210",
"germany": "213",
"greece": "230",
"holland": "207",
"hong kong": "108",
"hungary": "227",
"india": "123",
"indonesia": "118",
"ireland": "206",
"israel": "143",
"italy": "220",
"kazakhstan": "153",
"korea": "103",
"kuwait": "138",
"malaysia": "113",
"mexico": "305",
"myanmar": "122",
"netherlands": "207",
"new zealand": "606",
"nigeria": "524",
"norway": "202",
"oman": "141",
"pakistan": "124",
"peru": "407",
"philippines": "117",
"poland": "223",
"portugal": "217",
"prc": "105",
"qatar": "140",
"romania": "231",
"russia": "224",
"saudi arabia": "137",
"singapore": "112",
"south africa": "551",
"south korea": "103",
"spain": "218",
"sri lanka": "125",
"sweden": "203",
"switzerland": "215",
"taiwan": "106",
"thailand": "111",
"turkey": "234",
"uae": "147",
"uk": "205",
"ukraine": "238",
"united arab emirates": "147",
"united kingdom": "205",
"united states": "304",
"us": "304",
"usa": "304",
"vietnam": "110"
},
"korea_trade": {
"america": "US",
"argentina": "AR",
"australia": "AU",
"austria": "AT",
"bangladesh": "BD",
"belgium": "BE",
"brazil": "BR",
"burma": "MM",
"canada": "CA",
"chile": "CL",
"china": "CN",
"colombia": "CO",
"czechia": "CZ",
"denmark": "DK",
"egypt": "EG",
"finland": "FI",
"france": "FR",
"germany": "DE",
"greece": "GR",
"holland": "NL",
"hong kong": "HK",
"hungary": "HU",
"india": "IN",
"indonesia": "ID",
"ireland": "IE",
"israel": "IL",
"italy": "IT",
"japan": "JP",
"kazakhstan": "KZ",
"kuwait": "KW",
"malaysia": "MY",
"mexico": "MX",
"myanmar": "MM",
"netherlands": "NL",
"new zealand": "NZ",
"nigeria": "NG",
"norway": "NO",
"oman": "OM",
"pakistan": "PK",
"peru": "PE",
"philippines": "PH",
"poland": "PL",
"portugal": "PT",
"prc": "CN",
"qatar": "QA",
"romania": "RO",
"russia": "RU",
"saudi arabia": "SA",
"singapore": "SG",
"south africa": "ZA",
"spain": "ES",
"sri lanka": "LK",
"sweden": "SE",
"switzerland": "CH",
"taiwan": "TW",
"thailand": "TH",
"turkey": "TR",
"uae": "AE",
"uk": "GB",
"ukraine": "UA",
"united arab emirates": "AE",
"united kingdom": "GB",
"united states": "US",
"us": "US",
"usa": "US",
"vietnam": "VN"
},
"taiwan_trade": {
"america": "US",
"argentina": "AR",
"australia": "AU",
"austria": "AT",
"bangladesh": "BD",
"belgium": "BE",
"brazil": "BR",
"burma": "MM",
"canada": "CA",
"chile": "CL",
"china": "CN",
"colombia": "CO",
"czechia": "CZ",
"denmark": "DK",
"egypt": "EG",
"finland": "FI",
"france": "FR",
"germany": "DE",
"greece": "GR",
"holland": "NL",
"hong kong": "HK",
"hungary": "HU",
"india": "IN",
"indonesia": "ID",
"ireland": "IE",
"israel": "IL",
"italy": "IT",
"japan": "JP",
"kazakhstan": "KZ",
"korea": "KR",
"kuwait": "KW",
"malaysia": "MY",
"mexico": "MX",
"myanmar": "MM",
"netherlands": "NL",
"new zealand": "NZ",
"nigeria": "NG",
"norway": "NO",
"oman": "OM",
"pakistan": "PK",
"peru": "PE",
"philippines": "PH",
"poland": "PL",
"portugal": "PT",
"prc": "CN",
"qatar": "QA",
"romania": "RO",
"russia": "RU",
"saudi arabia": "SA",
"singapore": "SG",
"south africa": "ZA",
"south korea": "KR",
"spain": "ES",
"sri lanka": "LK",
"sweden": "SE",
"switzerland": "CH",
"taiwan": "TW",
"thailand": "TH",
"turkey": "TR",
"uae": "AE",
"uk": "GB",
"ukraine": "UA",
"united arab emirates": "AE",
"united kingdom": "GB",
"united states": "US",
"us": "US",
"usa": "US",
"vietnam": "VN"
},
"us_census_hs": {
"argentina": "3570",
"australia": "6021",
"austria": "4330",
"bangladesh": "5380",
"belgium": "4231",
"brazil": "3510",
"burma": "5460",
"canada": "1220",
"chile": "3370",
"china": "5700",
"colombia": "3010",
"czechia": "4351",
"denmark": "4099",
"egypt": "7290",
"finland": "4050",
"france": "4279",
"germany": "4280",
"greece": "4840",
"holland": "4210",
"hong kong": "5820",
"hungary": "4370",
"india": "5330",
"indonesia": "5600",
"ireland": "4190",
"israel": "5081",
"italy": "4759",
"japan": "5880",
"kazakhstan": "4634",
"korea": "5800",
"kuwait": "5130",
"malaysia": "5570",
"mexico": "2010",
"myanmar": "5460",
"netherlands": "4210",
"new zealand": "6141",
"nigeria": "7530",
"north korea": "5790",
"norway": "4039",
"oman": "5230",
"pakistan": "5350",
"peru": "3330",
"philippines": "5650",
"poland": "4550",
"portugal": "4710",
"prc": "5700",
"qatar": "5180",
"romania": "4850",
"russia": "4621",
"saudi arabia": "5170",
"singapore": "5590",
"south africa": "7910",
"south korea": "5800",
"spain": "4700",
"sri lanka": "5420",
"sweden": "4010",
"switzerland": "4419",
"taiwan": "5830",
"thailand": "5490",
"turkey": "4890",
"uae": "5200",
"uk": "4120",
"ukraine": "4623",
"united arab emirates": "5200",
"united kingdom": "4120",
"vietnam": "5520"
}
},
"partners": {
"china_customs": {
"101": "Afghanistan",
"102": "Bahrain",
"103": "Bangladesh",
"104": "Bhutan",
"105": "Brunei",
"106": "Myanmar",
"107": "Cambodia",
"108": "Cyprus",
"109": "Democratic People's Republic of Korea",
"110": "Hong Kong，China",
"111": "India",
"112": "Indonesia",
"113": "Iran",
"114": "Iraq",
"115": "Israel",
"116": "Japan",
"117": "Jordan",
"118": "Kuwait",
"119": "Lao",
"120": "Lebanon",
"121": "Macao,China",
"122": "Malaysia",
"123": "Maldives",
"124": "Mongolia",
"125": "Nepal",
"126": "Oman",
"127": "Pakistan",
"128": "Palestine",
"129": "Philippines",
"130": "Qatar",
"131": "Saudi Arabia",
"132": "Singapore",
"133": "Republic of Korea",
"134": "Sri Lanka",
"135": "Syria",
"136": "Thailand",
"137": "Türkiye",
"138": "United Arab Emirates",
"139": "Yemen",
"141": "Viet Nam",
"142": "China",
"143": "Taiwan，China",
"144": "Timor-Leste",
"145": "Kazakhstan",
"146": "Kyrgyzstan",
"147": "Tajikistan",
"148": "Turkmenistan",
"149": "Uzbekistan",
"150": "Georgia",
"151": "Armenia",
"152": "Azerbai jan",
"199": "Other Asian Territories",
"201": "Algeria",
"202": "Angola",
"203": "Benin",
"204": "Botswana",
"205": "Burundi",
"206": "Cameroon",
"207": "Canary Islands",
"208": "Cabo Verde",
"209": "Central African Republic",
"210": "Ceuta",
"211": "Chad",
"212": "Comoros",
"213": "Congo",
"214": "Djibouti",
"215": "Egypt",
"216": "Equatorial Guinea",
"217": "Ethiopia",
"218": "Gabon",
"219": "Gambia",
"220": "Ghana",
"221": "Guinea",
"222": "Guinea-Bissau",
"223": "Cote d'lvoire",
"224": "Kenya",
"225": "Liberia",
"226": "Libya",
"227": "Madagascar",
"228": "Malawi",
"229": "Mali",
"230": "Mauritania",
"231": "Mauritius",
"232": "Morocco",
"233": "Mozambique",
"234": "Namibia",
"235": "Niger",
"236": "Nigeria",
"237": "Réunion",
"238": "Rwanda",
"239": "Sao Tome and Principe",
"240": "Senegal",
"241": "Seychelles",
"242": "Sierra Leone",
"243": "Somalia",
"244": "South Africa",
"245": "Western Sahara",
"246": "Sudan",
"247": "Tanzania",
"248": "Togo",
"249": "Tunisia",
"250": "Uganda",
"251": "Burkina Faso",
"252": "Democratic Republic of Congo",
"253": "Zambia",
"254": "Zimbabwe",
"255": "Lesotho",
"256": "Melilla",
"257": "Swaziland",
"258": "Eritrea",
"259": "Mayotte",
"260": "South Sudan",
"261": "French Southern Territories",
"262": "British Indian Ocean Territory",
"263": "Saint Helena",
"299": "Other African Territories",
"301": "Belgium",
"302": "Denmark",
"303": "United Kingdom",
"304": "Germany",
"305": "France",
"306": "Ireland",
"307": "Italy",
"308": "Luxembourg",
"309": "Netherlands",
"310": "Greece",
"311": "Portugal",
"312": "Spain",
"313": "Albania",
"314": "Andorra",
"315": "Austria",
"316": "Bulgaria",
"318": "Finland",
"320": "Gibraltar",
"321": "Hungary",
"322": "Iceland",
"323": "Liechtenstein",
"324": "Malta",
"325": "Monaco",
"326": "Norway",
"327": "Poland",
"328": "Romania",
"329": "San Marino",
"330": "Sweden",
"331": "Switzerland",
"334": "Estonia",
"335": "Latvia",
"336": "Lithuania",
"337": "Georgia",
"338": "Armenia",
"339": "Azerbai jan",
"340": "Belarus",
"343": "Moldova",
"344": "Russia",
"347": "Ukraine",
"349": "349",
"350": "Slovenia",
"351": "Croatia",
"352": "Czechia（Czech Republic）",
"353": "Slovakia",
"354": "North Macedonia",
"355": "Bosnia and Herzegovina",
"356": "Holy See",
"357": "Faroe Islands",
"358": "Serbia",
"359": "Montenegro",
"360": "Aland Islands",
"361": "Guernsey",
"362": "Isle of Man",
"363": "Jersey",
"399": "Other European Territories",
"401": "Antigua & Barbuda",
"402": "Argentina",
"403": "Aruba",
"404": "Bahamas",
"405": "Barbados",
"406": "Belize",
"408": "Bolivia",
"409": "Bonaire",
"410": "Brazil",
"411": "Cayman Islands",
"412": "Chile",
"413": "Colombia",
"414": "Dominica",
"415": "Costa Rica",
"416": "Cuba",
"417": "Curacao",
"418": "Dominican Republic",
"419": "Ecuador",
"420": "French Guiana",
"421": "Grenada",
"422": "Guadeloupe",
"423": "Guatemala",
"424": "Guyana",
"425": "Haiti",
"426": "Honduras",
"427": "Jamaica",
"428": "Martinique",
"429": "Mexico",
"430": "Montserrat",
"431": "Nicaragua",
"432": "Panama",
"433": "Paraguay",
"434": "Peru",
"435": "Puerto Rico",
"436": "Saba",
"437": "Saint Lucia",
"438": "Saint Martin (French Part)",
"439": "Saint Vincent and the Grenadines",
"440": "El Salvador",
"441": "Suriname",
"442": "Trinidad and Tobago",
"443": "Turks and Caicos Islands",
"444": "Uruguay",
"445": "Venezuela",
"446": "British Virgin Islands",
"447": "Saint Kitts and Nevis",
"448": "Saint.Pierre and Miquelon",
"449": "Bonaire, Sint Eustatius and Saba",
"450": "Saint Barthélemy",
"451": "Bouvet Island",
"452": "Falkland Islands (Malvinas)",
"453": "South Georgia and the South Sandwich Islands",
"454": "Sint Maarten (Dutch part)",
"455": "United States Virgin Islands",
"456": "Anguilla",
"499": "Other Latin American Territories",
"501": "Canada",
"502": "United States",
"503": "Greenland",
"504": "Bermuda",
"505": "Saint.Pierre and Miquelon",
"599": "Other North American Territories",
"601": "Australia",
"602": "Cook Islands",
"603": "Fiji",
"604": "Gambier Islands",
"605": "Marquesas Islands",
"606": "Nauru",
"607": "New Caledonia",
"608": "Vanuatu",
"609": "New Zealand",
"610": "Norfolk Island",
"611": "Papua New Guinea",
"612": "Society Islands",
"613": "Solomon Islands",
"614": "Tonga",
"615": "Tuamotu Islands",
"616": "Tubai Islands",
"617": "Samoa",
"618": "Kiribati",
"619": "Tuvalu",
"620": "The Federated States of Micronesia",
"621": "Marshall Islands",
"622": "Palau",
"623": "French Polynesia",
"625": "Wallis and Futuna",
"626": "American Samoa",
"627": "Cocos (Keeling) Islands",
"628": "Christmas Island",
"629": "Guam",
"631": "Northern Mariana Islands",
"632": "Niue",
"633": "Pitcairn",
"634": "Tokelau",
"635": "United States Minor Outlying Islands",
"699": "Other Oceanian Territories",
"701": "Countries（Territories）Unknown",
"702": "UN and oth. int'l organizations"
},
"india_trade": {
"1": "AFGHANISTAN",
"101": "DENMARK",
"102": "DJIBOUTI",
"103": "DOMINIC REP",
"105": "DOMINICA",
"109": "ECUADOR",
"11": "ANGOLA",
"111": "EGYPT A RP",
"113": "EL SALVADOR",
"114": "ESTONIA",
"115": "ETHIOPIA",
"116": "ERITREA",
"117": "EQUTL GUINEA",
"12": "ANGUILLA",
"121": "FAROE IS.",
"122": "JERSEY",
"125": "FINLAND",
"127": "FIJI IS",
"129": "FRANCE",
"13": "ANTIGUA",
"131": "FR GUIANA",
"133": "FR POLYNESIA",
"14": "ANTARTICA",
"141": "GABON",
"143": "GAMBIA",
"145": "GEORGIA",
"147": "GERMANY",
"149": "GHANA",
"15": "ARGENTINA",
"151": "GIBRALTAR",
"155": "GREECE",
"157": "GREENLAND",
"159": "GRENADA",
"16": "ARMENIA",
"161": "GUADELOUPE",
"163": "GUAM",
"165": "GUATEMALA",
"167": "GUINEA",
"169": "GUINEA BISSAU",
"17": "AUSTRALIA",
"171": "GUYANA",
"175": "HAITI",
"177": "HONDURAS",
"179": "HONG KONG",
"181": "HUNGARY",
"185": "ICELAND",
"187": "INDONESIA",
"189": "IRAN",
"19": "AUSTRIA",
"191": "IRAQ",
"193": "IRELAND",
"195": "ISRAEL",
"196": "STATE OF PALEST",
"197": "ITALY",
"198": "VATICAN CITY",
"199": "COTE D' IVOIRE",
"20": "ARUBA",
"203": "JAMAICA",
"205": "JAPAN",
"207": "JORDAN",
"21": "AZERBAIJAN",
"212": "KAZAKHSTAN",
"213": "KENYA",
"214": "KIRIBATI REP",
"215": "KOREA DP RP",
"216": "KYRGHYZSTAN",
"217": "KOREA RP",
"219": "KUWAIT",
"223": "LAO PD RP",
"224": "LATVIA",
"225": "LEBANON",
"227": "LESOTHO",
"229": "LIBERIA",
"23": "BAHAMAS",
"231": "LIBYA",
"233": "LIECHTENSTEIN",
"234": "LITHUANIA",
"235": "LUXEMBOURG",
"239": "MACAO",
"240": "MACEDONIA",
"241": "MADAGASCAR",
"243": "MALAWI",
"245": "MALAYSIA",
"247": "MALDIVES",
"249": "MALI",
"25": "BAHARAIN IS",
"251": "MALTA",
"252": "MARSHALL ISLAND",
"253": "MARTINIQUE",
"255": "MAURITANIA",
"256": "MICRONESIA",
"257": "MAURITIUS",
"258": "MYANMAR",
"259": "MEXICO",
"260": "MOLDOVA",
"261": "MONGOLIA",
"262": "MONACO",
"263": "MONTSERRAT",
"265": "MOROCCO",
"267": "MOZAMBIQUE",
"269": "NAMIBIA",
"27": "BANGLADESH PR",
"271": "NAURU RP",
"273": "NEPAL",
"275": "NETHERLAND",
"277": "NETHERLANDANTIL",
"278": "SINT MAARTEN (DUTCH PART)",
"281": "NEW CALEDONIA",
"285": "NEW ZEALAND",
"287": "NICARAGUA",
"289": "NIGER",
"29": "BARBADOS",
"291": "NIGERIA",
"294": "N. MARIANA IS.",
"295": "NORFOLK IS",
"297": "NORWAY",
"3": "ALBANIA",
"301": "OMAN",
"309": "PAKISTAN IR",
"31": "BELIZE",
"310": "PALAU",
"311": "PANAMA REPUBLIC",
"315": "PAPUA N GNA",
"317": "PARAGUAY",
"319": "PERU",
"323": "PHILIPPINES",
"325": "POLAND",
"327": "PORTUGAL",
"329": "TIMOR LESTE",
"33": "BELGIUM",
"331": "PUERTO RICO",
"335": "QATAR",
"339": "REUNION",
"34": "MAYOTTE",
"343": "ROMANIA",
"344": "RUSSIA",
"345": "RWANDA",
"346": "SAN MARINO",
"349": "SAO TOME",
"35": "BENIN",
"351": "SAUDI ARAB",
"352": "SERBIA",
"353": "SENEGAL",
"355": "SEYCHELLES",
"356": "MONTENEGRO",
"357": "SIERRA LEONE",
"358": "SLOVAK REP",
"359": "SINGAPORE",
"360": "SLOVENIA",
"361": "SOLOMON IS",
"363": "SOMALIA",
"365": "SOUTH AFRICA",
"367": "SPAIN",
"369": "SRI LANKA DSR",
"37": "BERMUDA",
"373": "ST KITT N A",
"375": "ST LUCIA",
"379": "ST VINCENT",
"38": "BHUTAN",
"381": "SUDAN",
"382": "SOUTH SUDAN",
"383": "SURINAME",
"385": "SWAZILAND",
"387": "SWEDEN",
"389": "SWITZERLAND",
"39": "BOLIVIA",
"391": "SYRIA",
"393": "TAJIKISTAN",
"395": "TANZANIA REP",
"397": "THAILAND",
"399": "TOGO",
"40": "BOSNIA-HRZGOVIN",
"403": "TONGA",
"405": "TRINIDAD",
"407": "TUNISIA",
"409": "TURKEY",
"41": "BOTSWANA",
"410": "TURKMENISTAN",
"411": "TURKS C IS",
"413": "TUVALU",
"417": "UGANDA",
"419": "U ARAB EMTS",
"421": "U K",
"422": "UKRAINE",
"423": "U S A",
"424": "US MINOR OUTLYING ISLANDS",
"427": "URUGUAY",
"43": "BRAZIL",
"430": "UZBEKISTAN",
"431": "VANUATU REP",
"433": "VENEZUELA",
"437": "VIETNAM SOC REP",
"439": "VIRGIN IS US",
"447": "SAMOA",
"45": "BR VIRGN IS",
"453": "YEMEN REPUBLC",
"459": "CONGO D. REP.",
"461": "ZAMBIA",
"463": "ZIMBABWE",
"47": "BRUNEI",
"49": "BULGARIA",
"5": "ALGERIA",
"50": "BURKINA FASO",
"53": "BURUNDI",
"55": "BELARUS",
"56": "CAMBODIA",
"57": "CAMEROON",
"59": "CANADA",
"599": "UNSPECIFIED",
"63": "CAPE VERDE IS",
"65": "CAYMAN IS",
"67": "C AFRI REP",
"69": "CHAD",
"7": "AMERI SAMOA",
"73": "CHILE",
"75": "TAIWAN",
"77": "CHINA P RP",
"83": "COLOMBIA",
"85": "COMOROS",
"87": "CONGO P REP",
"89": "COOK IS",
"9": "ANDORRA",
"91": "COSTA RICA",
"92": "CROATIA",
"93": "CUBA",
"95": "CYPRUS",
"98": "CZECH REPUBLIC"
},
"japan_trade": {
"103": "Republic of Korea",
"105": "People's Republic of China",
"106": "Taiwan",
"107": "Mongolia",
"108": "Hong Kong",
"110": "Viet Nam",
"111": "Thailand",
"112": "Singapore",
"113": "Malaysia",
"116": "Brunei",
"117": "Philippines",
"118": "Indonesia",
"120": "Cambodia",
"121": "Laos",
"122": "Myanmar",
"123": "India",
"124": "Pakistan",
"125": "Sri Lanka",
"126": "Maldives",
"127": "Bangladesh",
"128": "Timor-Leste",
"129": "Macao",
"130": "Afghanistan",
"131": "Nepal",
"132": "Bhutan",
"133": "Iran",
"134": "Iraq",
"135": "Bahrain",
"137": "Saudi Arabia",
"138": "Kuwait",
"140": "Qatar",
"141": "Oman",
"143": "Israel",
"144": "Jordan",
"145": "Syria",
"146": "Lebanon",
"147": "United Arab Emirates",
"149": "Yemen",
"150": "Azerbaijan",
"151": "Armenia",
"152": "Uzbekistan",
"153": "Kazakhstan",
"154": "Kyrgyz",
"155": "Tajikistan",
"156": "Turkmenistan",
"157": "Georgia",
"158": "The West Bank and Gaza Strip",
"201": "Iceland",
"202": "Norway",
"203": "Sweden",
"204": "Denmark",
"205": "United Kingdom",
"206": "Ireland",
"207": "Netherlands",
"208": "Belgium",
"209": "Luxembourg",
"210": "France",
"211": "Monaco",
"212": "Andorra",
"213": "Germany",
"215": "Switzerland",
"217": "Portugal",
"218": "Spain",
"219": "Gibraltar (UK)",
"220": "Italy",
"221": "Malta",
"222": "Finland",
"223": "Poland",
"224": "Russia",
"225": "Austria",
"227": "Hungary",
"228": "Serbia",
"229": "Albania",
"230": "Greece",
"231": "Romania",
"232": "Bulgaria",
"233": "Cyprus",
"234": "Turkey",
"235": "Estonia",
"236": "Latvia",
"237": "Lithuania",
"238": "Ukraine",
"239": "Belarus",
"240": "Moldova",
"241": "Croatia",
"242": "Slovenia",
"243": "Bosnia and Herzegovina",
"244": "North Macedonia",
"245": "Czech Republic",
"246": "Slovakia",
"247": "Montenegro",
"248": "Kosovo",
"249": "Faroe Islands (Denmark)",
"250": "Vatican City",
"301": "Greenland (Denmark)",
"302": "Canada",
"304": "United States of America",
"305": "Mexico",
"306": "Guatemala",
"307": "Honduras",
"308": "Belize",
"309": "El Salvador",
"310": "Nicaragua",
"311": "Costa Rica",
"312": "Panama",
"314": "Bermuda (UK)",
"315": "The Bahamas",
"316": "Jamaica",
"317": "Turks, and Caicos Islands (UK)",
"319": "Barbados",
"320": "Trinidad and Tobago",
"321": "Cuba",
"322": "Haiti",
"323": "Dominican Republic",
"324": "Puerto Rico (USA)",
"325": "US Virgin Islands",
"326": "Netherlands Antilles",
"327": "French West Indies",
"328": "Cayman islands (UK)",
"329": "Grenada",
"330": "St.Lucia",
"331": "Antigua and Barbuda",
"332": "British Virgin Islands",
"333": "Dominica",
"334": "Monstserrat (UK)",
"335": "St.Christopher and Nevis",
"336": "St.Vincent",
"337": "British Anguilla",
"338": "St.Barthelemy (France)",
"401": "Colombia",
"402": "Venezuela",
"403": "Guyana",
"404": "Suriname",
"405": "French Guiana",
"406": "Ecuador",
"407": "Peru",
"408": "Bolivia",
"409": "Chile",
"410": "Brazil",
"411": "Paraguay",
"412": "Uruguay",
"413": "Argentina",
"414": "Falkland Islands and Dependencies (UK)",
"501": "Morocco",
"502": "Ceuta and Melilla (Spain)",
"503": "Algeria",
"504": "Tunisia",
"505": "Libya",
"506": "Egypt",
"507": "Sudan",
"508": "West Sahara",
"509": "Mauritania",
"510": "Senegal",
"511": "The Gambia",
"512": "Guinea-Bissau",
"513": "Guinea",
"514": "Sierra Leone",
"515": "Liberia",
"516": "Rep. of Cote d'Ivoire",
"517": "Ghana",
"518": "Togo",
"519": "Benin",
"520": "Mali",
"521": "Burkina Faso",
"522": "Cape Verde",
"523": "Canary Islands (Spain)",
"524": "Nigeria",
"525": "Niger",
"526": "Rwanda",
"527": "Cameroon",
"528": "Chad",
"529": "Central Africa",
"530": "Equatorial Guinea",
"531": "Gabon",
"532": "Republic of Congo",
"533": "Democratic Republic of Congo",
"534": "Burundi",
"535": "Angola",
"536": "Sao Tome and Principe",
"537": "St. Helena Island and Dependencies (UK)",
"538": "Ethiopia",
"539": "Djibouti",
"540": "Somalia",
"541": "Kenya",
"542": "Uganda",
"543": "Tanzania",
"544": "Seychelles",
"545": "Mozambique",
"546": "Madagascar",
"547": "Mauritius",
"548": "Reunion (France)",
"549": "Zimbabwe",
"550": "Namibia",
"551": "South Africa",
"552": "Lesotho",
"553": "Malawi",
"554": "Zambia",
"555": "Botswana",
"556": "Eswatini",
"558": "Comoros",
"559": "Eritrea",
"560": "Republic of South Sudan",
"601": "Australia",
"602": "Papua New Guinea",
"605": "Other Australian Territories",
"606": "New Zealand",
"607": "Cook",
"608": "Tokelau Islands (NZ)",
"609": "Niue",
"610": "Samoa",
"611": "Vanuatu",
"612": "Fiji",
"613": "Solomon Islands",
"614": "Tonga",
"615": "Kiribati",
"617": "Nauru",
"618": "New Caledonia (France)",
"619": "French Polynesia",
"620": "Guam (USA)",
"621": "American Samoa",
"622": "American Oceania",
"624": "Tuvalu",
"625": "Marshall",
"626": "Micronesia",
"627": "Northern Mariana Islands (USA)",
"628": "Palau",
"702": "Unknown"
},
"korea_trade": {
"AD": "Andorra",
"AE": "United Arab Emirates",
"AF": "Afghanistan",
"AG": "Antigua and Barbuda",
"AI": "Anguilla",
"AL": "Albania",
"AM": "Armenia",
"AN": "네덜란드 열도",
"AO": "Angola",
"AQ": "Antarctica",
"AR": "Argentina",
"AS": "American Samoa",
"AT": "Austria",
"AU": "Australia",
"AW": "Aruba",
"AZ": "Azerbaijan",
"BA": "Bosnia and Herzegovina",
"BB": "Barbados",
"BD": "Bangladesh",
"BE": "Belgium",
"BF": "Burkina Faso",
"BG": "Bulgaria",
"BH": "Bahrain",
"BI": "Burundi",
"BJ": "Benin",
"BL": "Saint Barthélemy",
"BM": "Bermuda",
"BN": "Brunei",
"BO": "Bolivia",
"BQ": "Bonaire, Sint Eustatius and Saba",
"BR": "Brazil",
"BS": "Bahamas",
"BT": "Bhutan",
"BV": "Bouvet Island",
"BW": "Botswana",
"BY": "Belarus",
"BZ": "Belize",
"CA": "Canada",
"CC": "Cocos (Keeling) Islands",
"CD": "Democratic Republic of the Congo",
"CF": "Central African Republic",
"CG": "Congo",
"CH": "Switzerland",
"CI": "Côte d'Ivoire",
"CK": "Cook Islands",
"CL": "Chile",
"CM": "Cameroon",
"CN": "China",
"CO": "Colombia",
"CR": "Costa Rica",
"CU": "Cuba",
"CV": "Cabo Verde",
"CW": "Curaçao",
"CX": "Christmas Island",
"CY": "Cyprus",
"CZ": "Czechia",
"DE": "Germany",
"DJ": "Djibouti",
"DK": "Denmark",
"DM": "Dominica",
"DO": "Dominican Republic",
"DZ": "Algeria",
"EC": "Ecuador",
"EE": "Estonia",
"EG": "Egypt",
"EH": "Western Sahara",
"ER": "Eritrea",
"ES": "Spain",
"ET": "Ethiopia",
"FI": "Finland",
"FJ": "Fiji",
"FK": "Falkland Islands (Malvinas)",
"FM": "Micronesia, Federated States of",
"FO": "Faroe Islands",
"FR": "France",
"GA": "Gabon",
"GB": "United Kingdom",
"GD": "Grenada",
"GE": "Georgia",
"GF": "French Guiana",
"GG": "Guernsey",
"GH": "Ghana",
"GI": "Gibraltar",
"GL": "Greenland",
"GM": "Gambia",
"GN": "Guinea",
"GP": "Guadeloupe",
"GQ": "Equatorial Guinea",
"GR": "Greece",
"GS": "South Georgia and the South Sandwich Islands",
"GT": "Guatemala",
"GU": "Guam",
"GW": "Guinea-Bissau",
"GY": "Guyana",
"HK": "Hong Kong",
"HM": "Heard Island and McDonald Islands",
"HN": "Honduras",
"HR": "Croatia",
"HT": "Haiti",
"HU": "Hungary",
"ID": "Indonesia",
"IE": "Ireland",
"IL": "Israel",
"IM": "Isle of Man",
"IN": "India",
"IO": "British Indian Ocean Territory",
"IQ": "Iraq",
"IR": "Iran",
"IS": "Iceland",
"IT": "Italy",
"JE": "Jersey",
"JM": "Jamaica",
"JO": "Jordan",
"JP": "Japan",
"KE": "Kenya",
"KG": "Kyrgyzstan",
"KH": "Cambodia",
"KI": "Kiribati",
"KM": "Comoros",
"KN": "Saint Kitts and Nevis",
"KW": "Kuwait",
"KY": "Cayman Islands",
"KZ": "Kazakhstan",
"LA": "Laos",
"LB": "Lebanon",
"LC": "Saint Lucia",
"LI": "Liechtenstein",
"LK": "Sri Lanka",
"LR": "Liberia",
"LS": "Lesotho",
"LT": "Lithuania",
"LU": "Luxembourg",
"LV": "Latvia",
"LY": "Libya",
"MA": "Morocco",
"MC": "Monaco",
"MD": "Moldova",
"ME": "Montenegro",
"MF": "Saint Martin (French part)",
"MG": "Madagascar",
"MH": "Marshall Islands",
"MK": "North Macedonia",
"ML": "Mali",
"MM": "Myanmar",
"MN": "Mongolia",
"MO": "Macao",
"MP": "Northern Mariana Islands",
"MQ": "Martinique",
"MR": "Mauritania",
"MS": "Montserrat",
"MT": "Malta",
"MU": "Mauritius",
"MV": "Maldives",
"MW": "Malawi",
"MX": "Mexico",
"MY": "Malaysia",
"MZ": "Mozambique",
"NA": "Namibia",
"NC": "New Caledonia",
"NE": "Niger",
"NG": "Nigeria",
"NI": "Nicaragua",
"NL": "Netherlands",
"NO": "Norway",
"NP": "Nepal",
"NR": "Nauru",
"NU": "Niue",
"NZ": "New Zealand",
"OM": "Oman",
"PA": "Panama",
"PE": "Peru",
"PF": "French Polynesia",
"PG": "Papua New Guinea",
"PH": "Philippines",
"PK": "Pakistan",
"PL": "Poland",
"PN": "Pitcairn",
"PR": "Puerto Rico",
"PS": "Palestine, State of",
"PT": "Portugal",
"PW": "Palau",
"PY": "Paraguay",
"QA": "Qatar",
"RE": "Réunion",
"RO": "Romania",
"RS": "Serbia",
"RU": "Russia",
"RW": "Rwanda",
"SA": "Saudi Arabia",
"SB": "Solomon Islands",
"SC": "Seychelles",
"SD": "Sudan",
"SE": "Sweden",
"SG": "Singapore",
"SH": "Saint Helena, Ascension and Tristan da Cunha",
"SI": "Slovenia",
"SJ": "Svalbard and Jan Mayen",
"SK": "Slovakia",
"SL": "Sierra Leone",
"SM": "San Marino",
"SN": "Senegal",
"SO": "Somalia",
"SR": "Suriname",
"SS": "South Sudan",
"ST": "Sao Tome and Principe",
"SV": "El Salvador",
"SX": "Sint Maarten (Dutch part)",
"SY": "Syria",
"SZ": "Eswatini",
"TC": "Turks and Caicos Islands",
"TD": "Chad",
"TF": "French Southern Territories",
"TG": "Togo",
"TH": "Thailand",
"TJ": "Tajikistan",
"TK": "Tokelau",
"TL": "Timor-Leste",
"TM": "Turkmenistan",
"TN": "Tunisia",
"TO": "Tonga",
"TR": "Türkiye",
"TT": "Trinidad and Tobago",
"TV": "Tuvalu",
"TW": "Taiwan",
"TZ": "Tanzania",
"UA": "Ukraine",
"UG": "Uganda",
"UM": "United States Minor Outlying Islands",
"US": "United States",
"UY": "Uruguay",
"UZ": "Uzbekistan",
"VA": "Holy See (Vatican City State)",
"VC": "Saint Vincent and the Grenadines",
"VE": "Venezuela",
"VG": "Virgin Islands, British",
"VI": "Virgin Islands, U.S.",
"VN": "Vietnam",
"VU": "Vanuatu",
"WF": "Wallis and Futuna",
"WS": "Samoa",
"YE": "Yemen",
"YT": "Mayotte",
"Z1": "국제통화기금",
"ZA": "South Africa",
"ZM": "Zambia",
"ZW": "Zimbabwe",
"ZZ": "Other countries"
},
"taiwan_trade": {
"AD": "Andorra",
"AE": "United Arab Emirates",
"AF": "Afghanistan",
"AG": "Antigua and Barbuda",
"AI": "Anguilla",
"AL": "Albania",
"AM": "Armenia",
"AN": "Netherlands Antilles",
"AO": "Angola",
"AQ": "Antarctica",
"AR": "Argentina",
"AS": "American Samoa",
"AT": "Austria",
"AU": "Australia",
"AW": "Aruba",
"AX": "Aland Islands",
"AZ": "Azerbaijan",
"BA": "Bosnia and Herzegovina",
"BB": "Barbados",
"BD": "Bangladesh",
"BE": "Belgium",
"BF": "Burkina Faso",
"BG": "Bulgaria",
"BH": "Bahrain",
"BI": "Burundi",
"BJ": "Benin",
"BL": "Saint Barthelemy",
"BM": "Bermuda",
"BN": "Brunei Darussalam",
"BO": "Bolivia",
"BQ": "Bonaire, Sint Eustatius and Saba",
"BR": "Brazil",
"BS": "Bahamas",
"BT": "Bhutan",
"BV": "Bouvet Island",
"BW": "Botswana",
"BY": "Belarus",
"BZ": "Belize",
"CA": "Canada",
"CC": "Cocos (Keeling) Islands",
"CD": "Democratic Republic of the Congo",
"CF": "Central African Republic",
"CG": "Congo",
"CH": "Switzerland",
"CI": "Cote Divoire",
"CK": "Cook Islands",
"CL": "Chile",
"CM": "Cameroon",
"CN": "China",
"CO": "Colombia",
"CR": "Costa Rica",
"CU": "Cuba",
"CV": "Cape Verde",
"CW": "Curacao",
"CX": "Christmas Island",
"CY": "Cyprus",
"CZ": "Czech Republic",
"DE": "Germany",
"DJ": "Djibouti",
"DK": "Denmark",
"DM": "Dominica",
"DO": "Dominican Republic",
"DZ": "Algeria",
"EC": "Ecuador",
"EE": "Estonia",
"EG": "Egypt",
"EH": "Western Sahara",
"ER": "Eritrea",
"ES": "Spain",
"ET": "Ethiopia",
"FI": "Finland",
"FJ": "Fiji",
"FK": "Falkland Islands (Malvinas)",
"FM": "Micronesia(Federated Stated of)",
"FO": "Faroe Islands",
"FR": "France",
"GA": "Gabon",
"GB": "United Kingdom",
"GD": "Grenada",
"GE": "Georgia",
"GF": "French Guiana",
"GG": "Guernsey",
"GH": "Ghana",
"GI": "Gibraltar",
"GL": "Greenland",
"GM": "Gambia",
"GN": "Guinea",
"GP": "Guadeloupe",
"GQ": "Equatorial Guinea",
"GR": "Greece",
"GS": "South Georgia and the South Sandwich Islands",
"GT": "Guatemala",
"GU": "Guam",
"GW": "Guinea-Bissau",
"GY": "Guyana",
"HK": "Hong Kong",
"HM": "Heard and Mcdonald Islands",
"HN": "Honduras",
"HR": "Croatia",
"HT": "Haiti",
"HU": "Hungary",
"ID": "Indonesia",
"IE": "Ireland",
"IL": "Israel",
"IM": "Isle of Man",
"IN": "India",
"IO": "British Indian Ocean Territory",
"IQ": "Iraq",
"IR": "Iran(Islamic Republic of)",
"IS": "Iceland",
"IT": "Italy",
"JE": "Jersey",
"JM": "Jamaica",
"JO": "Jordan",
"JP": "Japan",
"KE": "Kenya",
"KG": "Kyrgyzstan",
"KH": "Cambodia",
"KI": "Kiribati",
"KM": "Comoros",
"KN": "Saint Kitts and Nevis",
"KP": "Democratic Peoples Republic of Korea",
"KR": "Republic of Korea",
"KW": "Kuwait",
"KY": "Cayman Islands",
"KZ": "Kazakhstan",
"LA": "Lao Peoples Democratic Republic",
"LB": "Lebanon",
"LC": "Saint Lucia",
"LI": "Liechtenstein",
"LK": "Sri Lanka",
"LR": "Liberia",
"LS": "Lesotho",
"LT": "Lithuania",
"LU": "Luxembourg",
"LV": "Latvia",
"LY": "Libya",
"MA": "Morocco",
"MC": "Monaco",
"MD": "Republic of Moldova",
"ME": "Montenegro",
"MF": "Saint Martin",
"MG": "Madagascar",
"MH": "Marshall Islands",
"MK": "North Macedonia",
"ML": "Mali",
"MM": "Myanmar",
"MN": "Mongolia",
"MO": "Macau",
"MP": "Northern Mariana Islands",
"MQ": "Martinique",
"MR": "Mauritania",
"MS": "Montserrat",
"MT": "Malta",
"MU": "Mauritius",
"MV": "Maldives",
"MW": "Malawi",
"MX": "Mexico",
"MY": "Malaysia",
"MZ": "Mozambique",
"NA": "Namibia",
"NC": "New Caledonia",
"NE": "Niger",
"NF": "Norfolk Island",
"NG": "Nigeria",
"NI": "Nicaragua",
"NL": "Netherlands",
"NO": "Norway",
"NP": "Nepal",
"NR": "Nauru",
"NU": "Niue",
"NZ": "New Zealand",
"OM": "Oman",
"PA": "Panama",
"PE": "Peru",
"PF": "French Polynesia",
"PG": "Papua New Guinea",
"PH": "Philippines",
"PK": "Pakistan",
"PL": "Poland",
"PM": "St. Pierre and Miquelon",
"PN": "Pitcairn",
"PR": "Puerto Rico",
"PS": "Palestinian Territory, Occupied",
"PT": "Portugal",
"PW": "Palau",
"PY": "Paraguay",
"QA": "Qatar",
"RE": "Reunion",
"RO": "Romania",
"RS": "Serbia",
"RU": "Russian Federation",
"RW": "Rwanda",
"SA": "Saudi Arabia",
"SB": "Solomon Islands",
"SC": "Seychelles",
"SD": "Sudan",
"SE": "Sweden",
"SG": "Singapore",
"SH": "St. Helena",
"SI": "Slovenia",
"SJ": "Svalbard and Jan Mayen Islands",
"SK": "Slovakia",
"SL": "Sierra Leone",
"SM": "San Marino",
"SN": "Senegal",
"SO": "Somalia",
"SR": "Suriname",
"SS": "South Sudan",
"ST": "Sao Tome and Principe",
"SV": "El Salvador",
"SX": "Sint Maarten",
"SY": "Syrian Arab Republic",
"SZ": "Kingdom of Eswatini",
"TC": "Turks and Caicos Islands",
"TD": "Chad",
"TF": "French Southern Territories",
"TG": "Togo",
"TH": "Thailand",
"TJ": "Tajikistan",
"TK": "Tokelau",
"TL": "Timor-Leste",
"TM": "Turkmenistan",
"TN": "Tunisia",
"TO": "Tonga",
"TR": "Turkiye",
"TT": "Trinidad and Tobago",
"TV": "Tuvalu",
"TW": "Taiwan, Roc",
"TZ": "United Republic of Tanzania",
"UA": "Ukraine",
"UG": "Uganda",
"UM": "United States Minor Outlying Islands",
"US": "United States",
"UY": "Uruguay",
"UZ": "Uzbekistan",
"VA": "Vatican City State(Holy See)",
"VC": "Saint Vincent and the Grenadines",
"VE": "Venezuela",
"VG": "Virgin Islands (British)",
"VI": "Virgin Islands (U.S.)",
"VN": "Viet Nam",
"VU": "Vanuatu",
"WF": "Wallis and Futuna",
"WS": "Samoa",
"XC": "Tahiti",
"XK": "Kosovo",
"YE": "Yemen",
"YT": "Mayotte",
"ZA": "South Africa",
"ZM": "Zambia",
"ZW": "Zimbabwe",
"ZZ": "Unidentified Country"
},
"us_census_hs": {
"-": "Total For All Countries",
"0001": "Opec",
"0003": "European Union",
"0014": "Pacific Rim Countries",
"0017": "Cafta-Dr",
"0020": "Usmca (Nafta)",
"0021": "Twenty Latin American Republics",
"0022": "Oecd",
"0023": "Nato",
"0024": "Lafta",
"0025": "Euro Area",
"0026": "Apec",
"0027": "Asean",
"0028": "Cacm",
"1010": "Greenland",
"1220": "Canada",
"1610": "St Pierre And Miquelon",
"1XXX": "North America",
"2010": "Mexico",
"2050": "Guatemala",
"2080": "Belize",
"2110": "El Salvador",
"2150": "Honduras",
"2190": "Nicaragua",
"2230": "Costa Rica",
"2250": "Panama",
"2320": "Bermuda",
"2360": "Bahamas",
"2390": "Cuba",
"2410": "Jamaica",
"2430": "Turks And Caicos Islands",
"2440": "Cayman Islands",
"2450": "Haiti",
"2470": "Dominican Republic",
"2481": "Anguilla",
"2482": "British Virgin Islands",
"2483": "St Kitts And Nevis",
"2484": "Antigua And Barbuda",
"2485": "Montserrat",
"2486": "Dominica",
"2487": "St Lucia",
"2488": "St Vincent And The Grenadines",
"2489": "Grenada",
"2720": "Barbados",
"2740": "Trinidad And Tobago",
"2774": "Sint Maarten",
"2777": "Curacao",
"2779": "Aruba",
"2831": "Guadeloupe",
"2839": "Martinique",
"2XXX": "Central America",
"3010": "Colombia",
"3070": "Venezuela",
"3120": "Guyana",
"3150": "Suriname",
"3170": "French Guiana",
"3310": "Ecuador",
"3330": "Peru",
"3350": "Bolivia",
"3370": "Chile",
"3510": "Brazil",
"3530": "Paraguay",
"3550": "Uruguay",
"3570": "Argentina",
"3720": "Falkland Islands (Islas Malvinas)",
"3XXX": "South America",
"4000": "Iceland",
"4010": "Sweden",
"4031": "Svalbard, Jan Mayen Island",
"4039": "Norway",
"4050": "Finland",
"4091": "Faroe Islands",
"4099": "Denmark",
"4120": "United Kingdom",
"4190": "Ireland",
"4210": "Netherlands",
"4231": "Belgium",
"4239": "Luxembourg",
"4271": "Andorra",
"4272": "Monaco",
"4279": "France",
"4280": "Germany",
"4330": "Austria",
"4351": "Czech Republic",
"4359": "Slovakia",
"4370": "Hungary",
"4411": "Liechtenstein",
"4419": "Switzerland",
"4470": "Estonia",
"4490": "Latvia",
"4510": "Lithuania",
"4550": "Poland",
"4621": "Russia",
"4622": "Belarus",
"4623": "Ukraine",
"4631": "Armenia",
"4632": "Azerbaijan",
"4633": "Georgia",
"4634": "Kazakhstan",
"4635": "Kyrgyzstan",
"4641": "Moldova",
"4642": "Tajikistan",
"4643": "Turkmenistan",
"4644": "Uzbekistan",
"4700": "Spain",
"4710": "Portugal",
"4720": "Gibraltar",
"4730": "Malta",
"4751": "San Marino",
"4752": "Vatican City",
"4759": "Italy",
"4791": "Croatia",
"4792": "Slovenia",
"4793": "Bosnia And Herzegovina",
"4794": "Macedonia",
"4801": "Serbia",
"4803": "Kosovo",
"4804": "Montenegro",
"4810": "Albania",
"4840": "Greece",
"4850": "Romania",
"4870": "Bulgaria",
"4890": "Turkey",
"4910": "Cyprus",
"4XXX": "Europe",
"5020": "Syria",
"5040": "Lebanon",
"5050": "Iraq",
"5070": "Iran",
"5081": "Israel",
"5082": "Gaza Strip Administered By Israel",
"5083": "West Bank Administered By Israel",
"5110": "Jordan",
"5130": "Kuwait",
"5170": "Saudi Arabia",
"5180": "Qatar",
"5200": "United Arab Emirates",
"5210": "Yemen",
"5230": "Oman",
"5250": "Bahrain",
"5310": "Afghanistan",
"5330": "India",
"5350": "Pakistan",
"5360": "Nepal",
"5380": "Bangladesh",
"5420": "Sri Lanka",
"5460": "Burma",
"5490": "Thailand",
"5520": "Vietnam",
"5530": "Laos",
"5550": "Cambodia",
"5570": "Malaysia",
"5590": "Singapore",
"5600": "Indonesia",
"5601": "Timor-Leste",
"5610": "Brunei",
"5650": "Philippines",
"5660": "Macau",
"5682": "Bhutan",
"5683": "Maldives",
"5700": "China",
"5740": "Mongolia",
"5790": "Korea, North",
"5800": "Korea, South",
"5820": "Hong Kong",
"5830": "Taiwan",
"5880": "Japan",
"5XXX": "Asia",
"6021": "Australia",
"6022": "Norfolk Island",
"6023": "Cocos (Keeling) Islands",
"6024": "Christmas Island",
"6029": "Heard And Mcdonald Islands",
"6040": "Papua New Guinea",
"6141": "New Zealand",
"6142": "Cook Islands",
"6143": "Tokelau",
"6144": "Niue",
"6150": "Samoa",
"6223": "Solomon Islands",
"6224": "Vanuatu",
"6225": "Pitcairn Islands",
"6226": "Kiribati",
"6227": "Tuvalu",
"6412": "New Caledonia",
"6413": "Wallis And Futuna",
"6414": "French Polynesia",
"6810": "Marshall Islands",
"6820": "Micronesia",
"6830": "Palau",
"6862": "Nauru",
"6863": "Fiji",
"6864": "Tonga",
"6XXX": "Australia And Oceania",
"7140": "Morocco",
"7210": "Algeria",
"7230": "Tunisia",
"7250": "Libya",
"7290": "Egypt",
"7321": "Sudan",
"7323": "South Sudan",
"7370": "Western Sahara",
"7380": "Equatorial Guinea",
"7410": "Mauritania",
"7420": "Cameroon",
"7440": "Senegal",
"7450": "Mali",
"7460": "Guinea",
"7470": "Sierra Leone",
"7480": "Cote D'Ivoire",
"7490": "Ghana",
"7500": "Gambia",
"7510": "Niger",
"7520": "Togo",
"7530": "Nigeria",
"7540": "Central African Republic",
"7550": "Gabon",
"7560": "Chad",
"7580": "St Helena",
"7600": "Burkina Faso",
"7610": "Benin",
"7620": "Angola",
"7630": "Congo",
"7642": "Guinea-Bissau",
"7643": "Cabo Verde",
"7644": "Sao Tome And Principe",
"7650": "Liberia",
"7660": "Democratic Republic Of The Congo",
"7670": "Burundi",
"7690": "Rwanda",
"7700": "Somalia",
"7741": "Eritrea",
"7749": "Ethiopia",
"7770": "Djibouti",
"7780": "Uganda",
"7790": "Kenya",
"7800": "Seychelles",
"7810": "British Indian Ocean Territories",
"7830": "Tanzania",
"7850": "Mauritius",
"7870": "Mozambique",
"7880": "Madagascar",
"7881": "Mayotte",
"7890": "Comoros",
"7904": "Reunion",
"7905": "French Southern And Antarctic Lands",
"7910": "South Africa",
"7920": "Namibia",
"7930": "Botswana",
"7940": "Zambia",
"7950": "Eswatini",
"7960": "Zimbabwe",
"7970": "Malawi",
"7990": "Lesotho",
"7XXX": "Africa"
}
}
}